border_radius/__init__.py
border_radius/resources/border_radius.2048.png
border_radius-1.0.1.dist-info/METADATA
border_radius-1.0.1.dist-info/WHEEL
border_radius-1.0.1.dist-info/top_level.txt
border_radius-1.0.1.dist-info/RECORD
